sky130_pdk/__init__.py
sky130_pdk-0.0.0.dist-info/LICENSE
sky130_pdk-0.0.0.dist-info/METADATA
sky130_pdk-0.0.0.dist-info/WHEEL
sky130_pdk-0.0.0.dist-info/top_level.txt
sky130_pdk-0.0.0.dist-info/RECORD
