Metadata-Version: 2.1
Name: sky130-pdk
Version: 0.0.0
Summary: Python API for decoding information about Google's open source process design kit (PDK) for SkyWater's 130nm bulk process.
Author-email: Tim 'mithro' Ansell <tansell@google.com>
License: 
Project-URL: Homepage, https://github.com/google/skywater-pdk
Project-URL: Bug Tracker, https://github.com/google/skywater-pdk/issues
Classifier: Programming Language :: Python :: 3
Classifier: License :: OSI Approved :: Apache Software License
Classifier: Operating System :: OS Independent
Requires-Python: >=3.7
License-File: LICENSE
